{
    "homepage": "https://www.aardio.com/",
    "description": "A Windows desktop rapid programming platform",
    "version": "35.55.0",
    "license": "freeware",
    "url": "https://ide.update.aardio.com/releases/aardio.7z",
    "hash": "63a148f90b56cb628aef4f412d2a2f7d228b30566977ba7fbbe1162716bd3195",
    "bin": "aardio.exe",
    "shortcuts": [
        [
            "aardio.exe",
            "aardio"
        ]
    ],
    "persist": "config\\USR.CFG",
    "checkver": {
        "url": "http://ide.update.aardio.com/check/",
        "regex": "\"version\":\"([\\d.]+)\""
    },
    "autoupdate": {
        "url": "https://ide.update.aardio.com/releases/aardio.7z"
    }
}
