{
    "version": "40.103.8",
    "description": "A Windows desktop rapid programming platform",
    "homepage": "https://www.aardio.com/",
    "license": "freeware",
    "url": "https://www.aardio.com/download/ide/aardio.7z",
    "hash": "df45f26f3469f08dcec006c8d933b2cc73f3ab625970d1c47016e06487740eac",
    "shortcuts": [
        [
            "aardio.exe",
            "aardio"
        ]
    ],
    "persist": "config\\USR.CFG",
    "checkver": {
        "url": "https://ide.update.aardio.com/log/",
        "regex": "aardio v([\\d\\.]+)"
    },
    "autoupdate": {
        "url": "https://www.aardio.com/download/ide/aardio.7z"
    }
}
