{
    "homepage": "https://www.abareplace.com/",
    "version": "2.6",
    "license": "shareware",
    "url": "https://www.abareplace.com/AbaReplace26portable.zip",
    "hash": "87c15fda15ff49fef921e244a39a1ab8253cc949786c207e15424eeea9f6d12b",
    "bin": "AbaReplace.exe",
    "persist": [
        "AbaReplace.ini",
        "UndoInfo"
    ],
    "shortcuts": [
        [
            "AbaReplace.exe",
            "Aba Search & Replace"
        ]
    ],
    "checkver": {
        "url": "https://www.abareplace.com/download/",
        "regex": "Aba Search and Replace ([\\d.]+) installer"
    },
    "autoupdate": {
        "url": "https://www.abareplace.com/AbaReplace$cleanVersionportable.zip"
    }
}
