{
    "version": "2.5.10",
    "description": "All-in-one collaboration platform for API documentation, API debugging, API Mock and API test automation.",
    "homepage": "https://apifox.com",
    "license": "Freeware",
    "architecture": {
        "64bit": {
            "url": "https://cdn.apifox.cn/download/2.5.10/Apifox-2.5.10.exe#/dl.7z",
            "hash": "sha512:056b170942dc9cb06ce81567e210c28b13b8b3db2eb55e2221d7f305828f278c360002e4ffd51a6393ea33a43dfbd533a9ea014454d8f1385e51cd126f2fc630",
            "pre_install": [
                "Expand-7zipArchive \"$dir\\`$PLUGINSDIR\\app-64.7z\" \"$dir\"",
                "Remove-Item \"$dir\\`$*\", \"$dir\\Uninstall*\" -Force -Recurse"
            ]
        },
        "32bit": {
            "url": "https://cdn.apifox.cn/download/2.5.10/Apifox-windows-x86-2.5.10.exe#/dl.7z",
            "hash": "sha512:68af341e1bf906d09a2e4262e8cbc8b11c087952bd9ecd654ce21f1a09690b3952dc606c982db4e2fd1189acaa40a6ff5125c718ea270c96ec5b2f10b5f76641",
            "pre_install": [
                "Expand-7zipArchive \"$dir\\`$PLUGINSDIR\\app-32.7z\" \"$dir\"",
                "Remove-Item \"$dir\\`$*\", \"$dir\\Uninstall*\" -Force -Recurse"
            ]
        }
    },
    "shortcuts": [
        [
            "Apifox.exe",
            "Apifox",
            "--user-data-dir=\"$dir\\UserData\""
        ]
    ],
    "persist": "UserData",
    "checkver": {
        "url": "https://cdn.apifox.cn/download/latest.yml",
        "regex": "version: ([\\d.]+)"
    },
    "autoupdate": {
        "architecture": {
            "64bit": {
                "url": "https://cdn.apifox.cn/download/$version/Apifox-$version.exe#/dl.7z",
                "hash": {
                    "url": "https://cdn.apifox.cn/download/latest.yml",
                    "regex": "sha512: $base64"
                }
            },
            "32bit": {
                "url": "https://cdn.apifox.cn/download/$version/Apifox-windows-x86-$version.exe#/dl.7z",
                "hash": {
                    "url": "https://cdn.apifox.cn/download/x32/latest.yml",
                    "regex": "sha512: $base64"
                }
            }
        }
    }
}
