{
    "version": "3.0.0",
    "description": "A free, lightweight, open source alternative to iTunes and other Apple Music applications based on Electron 13.1.0",
    "homepage": "https://github.com/Apple-Music-Electron/Apple-Music-Electron",
    "license": "MIT",
    "architecture": {
        "64bit": {
            "url": "https://ghproxy.com/https://github.com/Apple-Music-Electron/Apple-Music-Electron/releases/download/v3.0.0/Apple-Music-Setup-3.0.0.exe#/dl.7z",
            "hash": "1bf09a1fff643c5741af21f8160b2e70caad62d0584ed2b271b49bd3c2efd57f",
            "pre_install": [
                "Expand-7zipArchive \"$dir\\`$PLUGINSDIR\\app-64.7z\" \"$dir\"",
                "Remove-Item \"$dir\\`$*\", \"$dir\\Uninst*\" -Force -Recurse"
            ]
        }
    },
    "shortcuts": [
        [
            "Apple Music.exe",
            "Apple Music"
        ]
    ],
    "checkver": "github",
    "autoupdate": {
        "architecture": {
            "64bit": {
                "url": "https://ghproxy.com/https://github.com/Apple-Music-Electron/Apple-Music-Electron/releases/download/v$version/Apple-Music-Setup-$version.exe#/dl.7z"
            }
        },
        "hash": {
            "url": "https://ghproxy.com/https://github.com/Apple-Music-Electron/Apple-Music-Electron/releases/download/v$version/latest.yml",
            "mode": "extract",
            "regex": "sha512: $base64"
        }
    }
}
