{
    "version": "1.20.1",
    "description": "A bash cli framework, also a task runner.",
    "homepage": "https://github.com/sigoden/argc",
    "license": "Apache-2.0|MIT",
    "architecture": {
        "64bit": {
            "url": "https://ghproxy.com/https://github.com/sigoden/argc/releases/download/v1.20.1/argc-v1.20.1-x86_64-pc-windows-msvc.zip",
            "hash": "f77d9248111254e6cc402b94e56716de0a9ff37ae341e462bbca750467eef5f7"
        },
        "32bit": {
            "url": "https://ghproxy.com/https://github.com/sigoden/argc/releases/download/v1.20.1/argc-v1.20.1-i686-pc-windows-msvc.zip",
            "hash": "0de3b63a44b0b74a02f653b50a479c96b0165f7368e678f6569cc4e8e081b62d"
        }
    },
    "bin": "argc.exe",
    "checkver": "github",
    "autoupdate": {
        "architecture": {
            "64bit": {
                "url": "https://ghproxy.com/https://github.com/sigoden/argc/releases/download/v$version/argc-v$version-x86_64-pc-windows-msvc.zip"
            },
            "32bit": {
                "url": "https://ghproxy.com/https://github.com/sigoden/argc/releases/download/v$version/argc-v$version-i686-pc-windows-msvc.zip"
            }
        }
    }
}
