{
    "homepage": "https://github.com/posit-dev/ark",
    "version": "0.1.234",
    "license": "MIT",
    "description": "Ark, an R kernel ",
    "url": "https://github.com/posit-dev/ark/releases/download/0.1.234/ark-0.1.234-windows-x64.zip",
    "hash": "b0fcc65912070a9de7e054d908ecfbc0975182dbdb798e904e833aec802f1726",
    "bin": "ark.exe",
    "checkver": {
        "url": "https://github.com/posit-dev/ark/tags",
        "regex": "/posit-dev/ark/releases/tag/([\\d]+\\.[\\d]+\\.[\\d]+)"
    },
    "autoupdate": {
        "url": "https://github.com/posit-dev/ark/releases/download/$version/ark-$version-windows-x64.zip"
    }
}
