{
    "url": "https://flcl.uk/public/Aslains_WoWs_Modpack_Installer_v.13.8.0_00.exe#installer.exe",
    "hash": "d07864e6d4364d991fcf9f5b216237f0e29ac3443229ad242ad2a68345cec12f",
    "version": "v.13.8.0_00",
    "license": "Unknown",
    "homepage": "https://aslain.com/index.php?/topic/2020-download-%E2%98%85-world-of-warships-%E2%98%85-modpack/",
    "installer": "installer.exe",
    "checkver": {
        "url": "https://aslain.com/index.php?/topic/2020-download-%E2%98%85-world-of-warships-%E2%98%85-modpack/",
        "regex": "https://flcl.uk/public/Aslains_WoWs_Modpack_Installer_(v[\\d._]+).exe"
    },
    "autoupdate": {
        "url": "https://flcl.uk/public/Aslains_WoWs_Modpack_Installer_$version.exe#installer.exe"
    }
}
