{
    "version": "1.36.39",
    "license": "Apache-2.0",
    "homepage": "https://aws.amazon.com/cli/",
    "description": "The AWS Command Line Interface (CLI) is a unified tool to manage your AWS services. With just one tool to download and configure, you can control multiple AWS services from the command line and automate them through scripts.",
    "url": "https://s3.amazonaws.com/aws-cli/AWSCLI64PY3-1.36.39.msi",
    "hash": "1b96bf4d3496303addd733b08e3c6a10b81a716a4cddbfc4ea359f938fd3c6ec",
    "extract_dir": "Amazon/AWSCLI",
    "bin": [
        [
            "runtime/python.exe",
            "awsv1",
            "-m awscli"
        ]
    ],
    "checkver": {
        "url": "https://pypi.org/rss/project/awscli/releases.xml",
        "xpath": "/rss/channel/item/title"
    },
    "autoupdate": {
        "url": "https://s3.amazonaws.com/aws-cli/AWSCLI64PY3-$version.msi"
    }
}
