{
    "checkver": {
        "url": "https://www.powershellgallery.com/api/v2/Packages()?$filter=Id%20eq%20'Az.Billing'%20and%20IsLatestVersion%20eq%20true",
        "replace": "${ver}",
        "regex": "(?i)<d:Version>(?<ver>[^<]+)<.d:Version>"
    },
    "hash": "sha512:90d63a627b2a8c2209127fb1bf3af620cf7ce61ca86b246b19e64ca4a85c3b25eaf23c52bc6682acec9b811ab6d0bce7b8eac365e40077b810a981606eae2f28",
    "description": "Microsoft Azure PowerShell - Billing service cmdlets for Azure Resource Manager in Windows PowerShell and PowerShell Core.  For information on Billing, please visit the following: https://learn.microsoft.com/azure/billing/",
    "psmodule": {
        "name": "Az.Billing"
    },
    "homepage": "https://www.powershellgallery.com/packages/Az.Billing",
    "autoupdate": {
        "url": "https://www.powershellgallery.com/api/v2/Package/Az.Billing/$version#/mod.nupkg",
        "hash": {
            "url": "https://www.powershellgallery.com/api/v2/Packages()?$filter=Id eq 'Az.Billing' and Version eq '$version'",
            "regex": "<d:PackageHash>$base64<.d:PackageHash>"
        }
    },
    "license": {
        "identifier": "Refer to Webpage",
        "url": "https://aka.ms/azps-license"
    },
    "url": "https://www.powershellgallery.com/api/v2/Package/Az.Billing/2.0.4#/mod.nupkg",
    "depends": "Az.Accounts",
    "version": "2.0.4"
}
