{
    "license": {
        "url": "https://aka.ms/azps-license",
        "identifier": "Refer to Webpage"
    },
    "url": "https://www.powershellgallery.com/api/v2/Package/Az.CosmosDB/1.14.3#/mod.nupkg",
    "autoupdate": {
        "url": "https://www.powershellgallery.com/api/v2/Package/Az.CosmosDB/$version#/mod.nupkg",
        "hash": {
            "url": "https://www.powershellgallery.com/api/v2/Packages()?$filter=Id eq 'Az.CosmosDB' and Version eq '$version'",
            "regex": "<d:PackageHash>$base64<.d:PackageHash>"
        }
    },
    "psmodule": {
        "name": "Az.CosmosDB"
    },
    "hash": "sha512:5e95b007b29152df986e174ed7040041a8673e29709f187eeab807b9b05c9555e4c799b2d7323498214a10768c6930c1a23e29bd6d82c0293db771be8418a7d6",
    "description": "Microsoft Azure PowerShell - CosmosDB service cmdlets for Azure Resource Manager in Windows PowerShell and PowerShell Core.  For more information on CosmosDB, please visit the following: https://docs.microsoft.com/azure/cosmos-db/",
    "homepage": "https://www.powershellgallery.com/packages/Az.CosmosDB",
    "checkver": {
        "regex": "(?i)<d:Version>(?<ver>[^<]+)<.d:Version>",
        "url": "https://www.powershellgallery.com/api/v2/Packages()?$filter=Id%20eq%20'Az.CosmosDB'%20and%20IsLatestVersion%20eq%20true",
        "replace": "${ver}"
    },
    "version": "1.14.3"
}
