{
    "license": {
        "url": "https://aka.ms/azps-license",
        "identifier": "Refer to Webpage"
    },
    "url": "https://www.powershellgallery.com/api/v2/Package/Az.CosmosDB/1.14.1#/mod.nupkg",
    "autoupdate": {
        "url": "https://www.powershellgallery.com/api/v2/Package/Az.CosmosDB/$version#/mod.nupkg",
        "hash": {
            "url": "https://www.powershellgallery.com/api/v2/Packages()?$filter=Id eq 'Az.CosmosDB' and Version eq '$version'",
            "regex": "<d:PackageHash>$base64<.d:PackageHash>"
        }
    },
    "psmodule": {
        "name": "Az.CosmosDB"
    },
    "hash": "sha512:465e96405b506a46da9e725a50063ee4b924c3f6411013b1a73a09e4b228174a24b097449e79d339bee38fad86919cbf95be1fd60ad3891d024a6ec5ccc6529a",
    "description": "Microsoft Azure PowerShell - CosmosDB service cmdlets for Azure Resource Manager in Windows PowerShell and PowerShell Core.  For more information on CosmosDB, please visit the following: https://docs.microsoft.com/azure/cosmos-db/",
    "homepage": "https://www.powershellgallery.com/packages/Az.CosmosDB",
    "checkver": {
        "regex": "(?i)<d:Version>(?<ver>[^<]+)<.d:Version>",
        "url": "https://www.powershellgallery.com/api/v2/Packages()?$filter=Id%20eq%20'Az.CosmosDB'%20and%20IsLatestVersion%20eq%20true",
        "replace": "${ver}"
    },
    "version": "1.14.1"
}
