{
    "checkver": {
        "url": "https://www.powershellgallery.com/api/v2/Packages()?$filter=Id%20eq%20'Az.DataFactory'%20and%20IsLatestVersion%20eq%20true",
        "replace": "${ver}",
        "regex": "(?i)<d:Version>(?<ver>[^<]+)<.d:Version>"
    },
    "hash": "sha512:00b80eb6bdd95b5cd582da8447776808883b3bf92fb8da4e16e52c8ad4ce97825dff41272d21f1a04ca48a0137031b14de2a18254fa147dbd1defff8810640cf",
    "description": "Microsoft Azure PowerShell - Data Factory service cmdlets for Azure Resource Manager in Windows PowerShell and PowerShell Core.  For more information on Data Factory, please visit the following: https://learn.microsoft.com/azure/data-factory/",
    "psmodule": {
        "name": "Az.DataFactory"
    },
    "homepage": "https://www.powershellgallery.com/packages/Az.DataFactory",
    "autoupdate": {
        "url": "https://www.powershellgallery.com/api/v2/Package/Az.DataFactory/$version#/mod.nupkg",
        "hash": {
            "url": "https://www.powershellgallery.com/api/v2/Packages()?$filter=Id eq 'Az.DataFactory' and Version eq '$version'",
            "regex": "<d:PackageHash>$base64<.d:PackageHash>"
        }
    },
    "license": {
        "identifier": "Refer to Webpage",
        "url": "https://aka.ms/azps-license"
    },
    "url": "https://www.powershellgallery.com/api/v2/Package/Az.DataFactory/1.19.7#/mod.nupkg",
    "depends": "Az.Accounts",
    "version": "1.19.7"
}
