{
    "checkver": {
        "url": "https://www.powershellgallery.com/api/v2/Packages()?$filter=Id%20eq%20'Az.DataFactory'%20and%20IsLatestVersion%20eq%20true",
        "replace": "${ver}",
        "regex": "(?i)<d:Version>(?<ver>[^<]+)<.d:Version>"
    },
    "hash": "sha512:faa78650deed6645296b03e86f52a6de9d87352c18ce826a93eb14c020cb3f359848fb72b52e052ae0c559f3baa5c74894f1bf090daf6a0f7333752ce80c9afb",
    "description": "Microsoft Azure PowerShell - Data Factory service cmdlets for Azure Resource Manager in Windows PowerShell and PowerShell Core.  For more information on Data Factory, please visit the following: https://learn.microsoft.com/azure/data-factory/",
    "psmodule": {
        "name": "Az.DataFactory"
    },
    "homepage": "https://www.powershellgallery.com/packages/Az.DataFactory",
    "autoupdate": {
        "url": "https://www.powershellgallery.com/api/v2/Package/Az.DataFactory/$version#/mod.nupkg",
        "hash": {
            "url": "https://www.powershellgallery.com/api/v2/Packages()?$filter=Id eq 'Az.DataFactory' and Version eq '$version'",
            "regex": "<d:PackageHash>$base64<.d:PackageHash>"
        }
    },
    "license": {
        "identifier": "Refer to Webpage",
        "url": "https://aka.ms/azps-license"
    },
    "url": "https://www.powershellgallery.com/api/v2/Package/Az.DataFactory/1.20.0#/mod.nupkg",
    "depends": "Az.Accounts",
    "version": "1.20.0"
}
