{
    "version": "2.13.1",
    "description": "B站录播姬命令行版（BiliBili Stream Recorder CLI），哔哩哔哩直播自动录制工具",
    "homepage": "https://rec.danmuji.org/",
    "license": "GPL-3.0-only",
    "architecture": {
        "64bit": {
            "url": "https://ghproxy.com/https://github.com/Bililive/BililiveRecorder/releases/download/v2.13.1/BililiveRecorder-CLI-win-x64.zip",
            "hash": "cf795e949fe3e3fdb303c651daa3bc31fe38149a83794179a2f3606a64c1e916"
        }
    },
    "extract_dir": "win-x64",
    "bin": "BililiveRecorder.Cli.exe",
    "checkver": {
        "github": "https://github.com/Bililive/BililiveRecorder"
    },
    "autoupdate": {
        "architecture": {
            "64bit": {
                "url": "https://ghproxy.com/https://github.com/Bililive/BililiveRecorder/releases/download/v$version/BililiveRecorder-CLI-win-x64.zip"
            }
        }
    }
}
