{
    "autoupdate": {
        "extract_dir": "biliupR-v$version-x86_64-windows",
        "url": "https://github.com/ForgQi/biliup-rs/releases/download/v$version/biliupR-v$version-x86_64-windows.zip"
    },
    "bin": "biliup.exe",
    "checkver": "github",
    "description": "Bilibili command line casting tool",
    "extract_dir": "biliupR-v0.1.15-x86_64-windows",
    "hash": "30e5feb9b5262db91c2cdcccc45f72bb58c25463e69447af1c67245eb44de888",
    "homepage": "https://github.com/ForgQi/biliup-rs",
    "license": {
        "identifier": "MIT",
        "url": "https://github.com/ForgQi/biliup-rs/blob/master/LICENSE"
    },
    "persist": "cookies.json",
    "pre_install": "if (!(Test-Path \"$persist_dir\\cookies.json\")) { New-Item \"$dir\\cookies.json\" -ItemType \"file\" -Value \"{}\" | Out-Null }",
    "url": "https://github.com/ForgQi/biliup-rs/releases/download/v0.1.15/biliupR-v0.1.15-x86_64-windows.zip",
    "version": "0.1.15"
}
