{
    "version": "7.8b",
    "description": "(PRO版本)小巧精悍的数码照片浏览器",
    "homepage": "http://www.bykeer.com/app/bkviewer/index.php",
    "license": "Freeware",
    "architecture": {
        "64bit": {
            "url": "http://www.bykeer.com/app/bkviewer/bkviewer.pro.exe",
            "hash": "7b7188377aa139fb327b2dfc2eedef290129a6502d48d5391bbc8924ce0c5621"
        }
    },
    "bin": "bkviewer.pro.exe",
    "shortcuts": [
        [
            "bkviewer.pro.exe",
            "bkViewer PRO"
        ]
    ],
    "notes": "bkViewer PRO is NOT portable.",
    "checkver": {
        "regex": "<span class='bkvv'>v(.*?)</span>"
    },
    "autoupdate": {
        "architecture": {
            "64bit": {
                "url": "http://www.bykeer.com/app/bkviewer/bkviewer.pro.exe"
            }
        }
    }
}
