{
    "architecture": {
        "64bit": {
            "hash": "af1a526c5e287964ca2e1873a8444dda46fb08af497994258bf3f7bd7e74fd79",
            "url": "https://github.com/brave/brave-browser/releases/download/v1.48.11/brave-v1.48.11-win32-x64.zip"
        }
    },
    "autoupdate": {
        "architecture": {
            "64bit": {
                "url": "https://github.com/brave/brave-browser/releases/download/v$version/brave-v$version-win32-x64.zip"
            }
        }
    },
    "bin": [
        [
            "brave.exe",
            "brave-nightly"
        ]
    ],
    "changelog": "",
    "checkver": {
        "regex": "Nightly v([\\d.]+)",
        "url": "https://github.com/brave/brave-browser/releases"
    },
    "description": "Brave Nightly. Secure, Fast & Private Web Browser with Adblocker (nightly release)",
    "homepage": "https://brave.com/download-nightly/",
    "license": {
        "identifier": "Freeware,BSD-3-Clause,GPL-3.0-only,...",
        "url": "https://github.com/brave/brave-browser/blob/master/LICENSE"
    },
    "shortcuts": [
        [
            "brave.exe",
            "Brave Nightly"
        ]
    ],
    "version": "1.48.11"
}
