{
    "version": "192138",
    "description": "Secure, Fast & Private Web Browser with Adblocker",
    "homepage": "https://brave.com",
    "license": {
        "identifier": "MPL 2.0",
        "url": "https://github.com/brave/brave-browser/blob/master/LICENSE"
    },
    "architecture": {
        "64bit": {
            "url": "https://brave-browser-downloads.s3.brave.com/latest/brave_installer-x64.exe#/dl.7z",
            "hash": "852e5d9adc4cdc8751b1f40f3ac36c6efc5a97c3f86f8117d0bf15478a0cec21"
        },
        "32bit": {
            "url": "https://brave-browser-downloads.s3.brave.com/latest/brave_installer-ia32.exe#/dl.7z",
            "hash": "02985a2a57af8d4273a17d6aea3bfae0535516c4f05b4b00bad167d013ff9aaa"
        }
    },
    "pre_install": "Expand-7zipArchive \"$dir\\chrome.7z\" -ExtractDir 'Chrome-bin' -Removal",
    "bin": "brave.exe",
    "shortcuts": [
        [
            "brave.exe",
            "Brave"
        ]
    ],
    "checkver": {
        "url": "https://brave.com/latest/",
        "regex": "release-notes-v([\\d]+)"
    },
    "autoupdate": {
        "architecture": {
            "64bit": {
                "url": "https://brave-browser-downloads.s3.brave.com/latest/brave_installer-x64.exe#/dl.7z"
            },
            "32bit": {
                "url": "https://brave-browser-downloads.s3.brave.com/latest/brave_installer-ia32.exe#/dl.7z"
            }
        }
    }
}
