{
    "version": "1.13",
    "description": "A single-player strategy game set in the halls of a mysterious and randomly-generated dungeon",
    "homepage": "https://github.com/tmewett/BrogueCE",
    "license": "AGPL-3.0-only",
    "extract_dir": "BrogueCE-windows",
    "url": "https://ghproxy.com/https://github.com/tmewett/BrogueCE/releases/download/v1.13/BrogueCE-1.13-windows-x86_64.zip",
    "hash": "8f1c8d72ae226f7a39f7e7a9f5d848f03b4a08c7f4f17fe35d705989a7417fea",
    "persist": "keymap.txt",
    "bin": "brogue.exe",
    "shortcuts": [
        [
            "brogue.exe",
            "Brogue"
        ]
    ],
    "checkver": {
        "github": "https://github.com/tmewett/BrogueCE"
    },
    "autoupdate": {
        "url": "https://ghproxy.com/https://github.com/tmewett/BrogueCE/releases/download/v$version/BrogueCE-$version-windows-x86_64.zip"
    }
}
