{
    "version": "3.27.0",
    "description": "The command line interface for Buildkite, a scale-out delivery platform.",
    "homepage": "https://github.com/barnybug/cli53",
    "license": "MIT",
    "architecture": {
        "64bit": {
            "url": "https://github.com/buildkite/cli/releases/download/v3.27.0/bk_3.27.0_windows_amd64.zip",
            "hash": "523f6fcca987850e066faa44425cc35fe316897736ce052b18c0f2e24f3011cc"
        },
        "arm64": {
            "url": "https://github.com/buildkite/cli/releases/download/v3.27.0/bk_3.27.0_windows_arm64.zip",
            "hash": "704e2aeaac3200ded6143b768646fd1a61e497f070d0f14a8f0a4a9a7fe4189e"
        }
    },
    "bin": "bk.exe",
    "checkver": {
        "github": "https://github.com/buildkite/cli"
    },
    "autoupdate": {
        "architecture": {
            "64bit": {
                "url": "https://github.com/buildkite/cli/releases/download/v$version/bk_$version_windows_amd64.zip"
            },
            "arm64": {
                "url": "https://github.com/buildkite/cli/releases/download/v$version/bk_$version_windows_arm64.zip"
            }
        },
        "hash": {
            "url": "$baseurl/bk_$version_checksums.txt"
        }
    }
}
