{
    "version": "1.2.3-canary.19+7a918d24a",
    "description": "Incredibly fast JavaScript runtime, bundler, transpiler and package manager - all in one.",
    "homepage": "https://bun.sh/",
    "license": "MIT",
    "suggest": {
        "vcredist": "extras/vcredist2022"
    },
    "architecture": {
        "64bit": {
            "url": "https://github.com/oven-sh/bun/releases/download/canary/bun-windows-x64.zip",
            "hash": "347a224d44dd80ca3c3751e9b20bc5054fb5446a844e1f6597d697ee7669306b"
        }
    },
    "extract_dir": "bun-windows-x64",
    "bin": [
        "bun.exe",
        [
            "bun.exe",
            "bunx",
            "x"
        ]
    ],
    "checkver": {
        "script": [
            "$dl_url = 'https://github.com/oven-sh/bun/releases/download/canary/bun-windows-x64.zip'",
            "$dl = cache_path 'bun-canary' 'unknown' $dl_url",
            "$dl_dir = strip_ext $dl",
            "Invoke-WebRequest $dl_url -OutFile $dl",
            "Expand-Archive $dl $dl_dir",
            "$ver = & \"$dl_dir\\bun-windows-x64\\bun.exe\" --revision",
            "Move-Item -Force $dl (cache_path 'bun-canary' $ver $dl_url)",
            "Remove-Item $dl_dir -Recurse",
            "$ver"
        ],
        "regex": "(\\S+)"
    },
    "autoupdate": {
        "architecture": {
            "64bit": {
                "url": "https://github.com/oven-sh/bun/releases/download/canary/bun-windows-x64.zip"
            }
        }
    }
}
