{
    "version": "6.6.0",
    "description": "Check your files for data corruption and run quick file deduplication.",
    "homepage": "https://github.com/laktak/chkbit",
    "license": "MIT",
    "architecture": {
        "64bit": {
            "url": "https://github.com/laktak/chkbit/releases/download/v6.6.0/chkbit-windows-amd64.zip",
            "hash": "cf2922856c2499a9ea98775529a3bd25ca0c7e2fc41b8bb0f6f2c90f11fcc058"
        },
        "arm64": {
            "url": "https://github.com/laktak/chkbit/releases/download/v6.6.0/chkbit-windows-arm64.zip",
            "hash": "c225249da5e35508d3ef4e222382ea49db5d9deeb53dca2455d85f6bebae0056"
        }
    },
    "bin": "chkbit.exe",
    "checkver": "github",
    "autoupdate": {
        "architecture": {
            "64bit": {
                "url": "https://github.com/laktak/chkbit/releases/download/v$version/chkbit-windows-amd64.zip"
            },
            "arm64": {
                "url": "https://github.com/laktak/chkbit/releases/download/v$version/chkbit-windows-arm64.zip"
            }
        }
    }
}
