{
 "autoupdate": {
  "url": "https://github.com/crystal-lang/crystal/releases/download/$version/crystal-$version-windows-x86_64-msvc-unsupported.zip"
 },
 "bin": [
  "crystal.exe",
  "shards.exe"
 ],
 "checkver": {
  "github": "https://github.com/crystal-lang/crystal"
 },
 "depends": "vswhere",
 "description": "A language for humans and computers.",
 "hash": "d72b99c408535ce986df1b841e8f0862a3ff275f2f6d58af4d7857fa17829a95",
 "homepage": "https://crystal-lang.org",
 "license": {
  "identifier": "Apache-2.0",
  "url": "https://github.com/crystal-lang/crystal/raw/master/LICENSE"
 },
 "post_install": "If (Test-Path \"$env:LOCALAPPDATA\\crystal\\cache\") { Remove-Item \"$env:LOCALAPPDATA\\crystal\\cache\" -ErrorAction 'SilentlyContinue' -Recurse -Force }",
 "url": "https://github.com/crystal-lang/crystal/releases/download/1.7.0/crystal-1.7.0-windows-x86_64-msvc-unsupported.zip",
 "version": "1.7.0"
}