{
    "version": "114.0.1778.0",
    "description": "Close the loop on your developer cycle by automating testing of your website in Microsoft Edge (Chromium).",
    "homepage": "https://developer.microsoft.com/en-us/microsoft-edge/tools/webdriver",
    "license": {
        "identifier": "Freeware",
        "url": "https://az813057.vo.msecnd.net/webdriver/license.html"
    },
    "notes": "For legacy (EdgeHTML) version, see 'versions/edgedriver-legacy'.",
    "architecture": {
        "64bit": {
            "url": "https://msedgedriver.azureedge.net/114.0.1778.0/edgedriver_win64.zip",
            "hash": "fc8506d590d40de383e33d1c38076e35d63c62e4f846b39a9d0e1d5b71136beb"
        },
        "32bit": {
            "url": "https://msedgedriver.azureedge.net/114.0.1778.0/edgedriver_win32.zip",
            "hash": "20d187c5f2f0577c198ff3cf7b91dd6a7e05d8da1aa35700bcc31f911c864bf3"
        }
    },
    "bin": "msedgedriver.exe",
    "checkver": {
        "script": "Write-Output $([System.Text.Encoding]::Unicode.GetString((Invoke-WebRequest -URI https://msedgedriver.azureedge.net/LATEST_CANARY).Content))",
        "regex": "([\\d.]+)"
    },
    "autoupdate": {
        "architecture": {
            "64bit": {
                "url": "https://msedgedriver.azureedge.net/$version/edgedriver_win64.zip"
            },
            "32bit": {
                "url": "https://msedgedriver.azureedge.net/$version/edgedriver_win32.zip"
            }
        }
    }
}
