{
    "version": "1.2.36",
    "description": " A command line program to download hentai videos and images from multiple websites.",
    "homepage": "https://github.com/gan-of-culture/get-sauce",
    "license": "MIT",
    "architecture": {
        "64bit": {
            "url": "https://github.com/gan-of-culture/get-sauce/releases/download/v1.2.36/get-sauce_1.2.36_Windows_64-bit.zip",
            "hash": "f258e13561397096642198cd92c4088945b84efc7754de51aeeb7a13f9ffd728"
        },
        "32bit": {
            "url": "https://github.com/gan-of-culture/get-sauce/releases/download/v1.2.36/get-sauce_1.2.36_Windows_32-bit.zip",
            "hash": "ee7e91f85354de3569c3c86c6cdbe4dac8022f9c9fc1bbc15771f6cbfaff1a7b"
        },
        "arm64": {
            "url": "https://github.com/gan-of-culture/get-sauce/releases/download/v1.2.36/get-sauce_1.2.36_Windows_arm64.zip",
            "hash": "6fe41c232d16415c446a7e737dbabd5305e0c24862be7b2fb1c4381cdb07e467"
        }
    },
    "bin": "get-sauce.exe",
    "checkver": "github",
    "autoupdate": {
        "architecture": {
            "64bit": {
                "url": "https://github.com/gan-of-culture/get-sauce/releases/download/v$version/get-sauce_$version_Windows_64-bit.zip"
            },
            "32bit": {
                "url": "https://github.com/gan-of-culture/get-sauce/releases/download/v$version/get-sauce_$version_Windows_32-bit.zip"
            },
            "arm64": {
                "url": "https://github.com/gan-of-culture/get-sauce/releases/download/v$version/get-sauce_$version_Windows_arm64.zip"
            }
        }
    }
}
