{
 "architecture": {
  "64bit": {
   "hash": "a995e6017b30493037967e80bb19d7558c7d9218b40fb05d92f6cb863d81ffce",
   "url": "https://www.giadamusic.com/data/giada-v0.23.0-x86_64-windows.zip"
  }
 },
 "autoupdate": {
  "architecture": {
   "64bit": {
    "url": "https://www.giadamusic.com/data/giada-v$version-x86_64-windows.zip"
   }
  }
 },
 "checkver": {
  "github": "https://github.com/monocasual/giada"
 },
 "description": "Open-source minimalistic music production tool",
 "homepage": "https://www.giadamusic.com/",
 "license": "GPL-3.0-only",
 "shortcuts": [
  [
   "giada.exe",
   "Giada"
  ]
 ],
 "version": "0.23.0"
}