{
 "autoupdate": {
  "extract_dir": "Greenfish Icon Editor Pro $version",
  "url": "http://greenfishsoftware.org/dl.php?filename=gfie$version.zip#/gfie.zip"
 },
 "checkver": {
  "regex": "gfie([\\d.]+).zip",
  "url": "http://greenfishsoftware.org/gfie.php"
 },
 "description": "Greenfish Icon Editor Pro (GFIE Pro) is a powerful open source image editor, especially suitable for creating icons, cursors, animations and icon libraries.",
 "extract_dir": "Greenfish Icon Editor Pro 4.0",
 "hash": "22a11def5cdfba367e37e86be04f826f7943d4981f16fbc685d205506d9f678f",
 "homepage": "http://greenfishsoftware.org/gfie.php",
 "shortcuts": [
  [
   "gfie64.exe",
   "Greenfish Icon Editor"
  ]
 ],
 "url": "http://greenfishsoftware.org/dl.php?filename=gfie4.0.zip#/gfie.zip",
 "version": "4.0"
}