{
    "architecture": {
        "64bit": {
            "hash": "d9352c6f8df5b25b071d4f212b3b806525d662e592c6860b50bb9e568332978b",
            "url": "https://github.com/alexmercerind2/harmonoid-releases/releases/download/v0.3.4/harmonoid-windows-setup.exe"
        }
    },
    "autoupdate": {
        "architecture": {
            "64bit": {
                "url": "https://github.com/alexmercerind2/harmonoid-releases/releases/download/v$version/harmonoid-windows-setup.exe"
            }
        }
    },
    "checkver": {
        "github": "https://github.com/alexmercerind2/harmonoid-releases"
    },
    "description": "Elegant music app to play & manage music library. Time-synced lyrics, playlists & visuals. YouTube Music.",
    "homepage": "https://github.com/harmonoid/harmonoid",
    "innosetup": true,
    "license": {
        "identifier": "Proprietary",
        "url": "https://raw.githubusercontent.com/harmonoid/harmonoid/master/EULA.txt"
    },
    "shortcuts": [
        [
            "harmonoid.exe",
            "Harmonoid"
        ]
    ],
    "version": "0.3.4"
}
