{
 "architecture": {
  "64bit": {
   "extract_dir": "kopia-0.12.1-windows-x64",
   "hash": "8af685fb15f5eda0f7fc98354d6a7ebb4600e55bf6899bd35453cb6a89b4f682",
   "url": "https://github.com/kopia/kopia/releases/download/v0.12.1/kopia-0.12.1-windows-x64.zip"
  }
 },
 "autoupdate": {
  "architecture": {
   "64bit": {
    "extract_dir": "kopia-$version-windows-x64",
    "url": "https://github.com/kopia/kopia/releases/download/v$version/kopia-$version-windows-x64.zip"
   }
  },
  "hash": {
   "url": "$baseurl/checksums.txt"
  }
 },
 "bin": "kopia.exe",
 "checkver": {
  "github": "https://github.com/kopia/kopia"
 },
 "description": "Fast and secure open source backup.",
 "homepage": "https://kopia.io/",
 "license": "Apache-2.0",
 "version": "0.12.1"
}