{
    "architecture": {
        "64bit": {
            "hash": "7f5d3d1b294ce43367cbcc15e508d36198b1313d9e15ba1b1b706c4c7565e32f",
            "url": "https://github.com/tdewolff/minify/releases/download/v2.12.2/minify_windows_amd64.zip"
        }
    },
    "autoupdate": {
        "architecture": {
            "64bit": {
                "hash": {
                    "url": "https://github.com/tdewolff/minify/releases/download/v$version/checksums.txt"
                },
                "url": "https://github.com/tdewolff/minify/releases/download/v$version/minify_windows_amd64.zip"
            }
        }
    },
    "bin": "minify.exe",
    "checkver": {
        "github": "https://github.com/tdewolff/minify"
    },
    "description": "Go minifiers for web formats",
    "homepage": "https://go.tacodewolff.nl/minify",
    "license": "MIT",
    "version": "2.12.2"
}
