{
    "autoupdate": {
        "url": "https://github.com/Hydr8gon/NooDS/releases/download/release/noods-windows.zip"
    },
    "bin": "noods.exe",
    "checkver": {
        "regex": "Run ([0-9]*) of Automatic Builds",
        "url": "https://github.com/Hydr8gon/NooDS/actions/workflows/autobuild.yml?query=branch%3Amaster+is%3Asuccess"
    },
    "description": "A (hopefully!) speedy DS emulator ",
    "hash": "f189f5ff1351c0665e5dcfb36720c0a2601a4f3253da800b2dfa00972de3410e",
    "homepage": "https://github.com/Hydr8gon/NooDS",
    "license": "GPL-2.0",
    "shortcuts": [
        [
            "noods.exe",
            "NooDS"
        ]
    ],
    "url": "https://github.com/Hydr8gon/NooDS/releases/download/release/noods-windows.zip",
    "version": "456"
}
