{
    "version": "28.1",
    "description": "Video recording and live streaming software(Download from TUNA mirror).",
    "homepage": "https://obsproject.com",
    "license": "GPL-2.0-only",
    "notes": [
        "Add Virtual Camera module by running: \"$dir\\data\\obs-plugins\\win-dshow\\virtualcam-install.bat\"",
        "Remove it by running: \"$dir\\data\\obs-plugins\\win-dshow\\virtualcam-uninstall.bat\""
    ],
    "architecture": {
        "64bit": {
            "url": "https://mirrors.tuna.tsinghua.edu.cn/github-release/obsproject/obs-studio/OBS%20Studio%2028.1/OBS-Studio-28.1-Full-x64.zip",
            "hash": "eef5acbc6b25c0a080d21b4d5a238c3f6451863b991d4f953d463e7d5a648277",
            "shortcuts": [
                [
                    "bin\\64bit\\obs64.exe",
                    "OBS Studio"
                ]
            ]
        }
    },
    "pre_install": "if (!(Test-Path \"$persist_dir\\portable_mode.txt\")) { New-Item \"$dir\\portable_mode.txt\" | Out-Null }",
    "persist": [
        "config",
        "portable_mode.txt"
    ],
    "checkver": {
        "url": "https://mirrors.tuna.tsinghua.edu.cn/github-release/obsproject/obs-studio/",
        "regex": "OBS Studio ([\\d.]+)",
        "reverse": true
    },
    "autoupdate": {
        "architecture": {
            "64bit": {
                "url": "https://mirrors.tuna.tsinghua.edu.cn/github-release/obsproject/obs-studio/OBS%20Studio%20$version/OBS-Studio-$version-Full-x64.zip"
            }
        }
    }
}
