{
 "##": "Duplicate (alias) of the odin-dev package",
 "architecture": {
  "64bit": {
   "hash": "17fe50d8980637c3be9e4880bd6eaf9fe7a025d6600cf386af99144caf3a2ce9",
   "url": "https://github.com/odin-lang/Odin/releases/download/dev-2022-12/odin-windows-amd64-dev-2022-12.zip"
  }
 },
 "autoupdate": {
  "architecture": {
   "64bit": {
    "url": "https://github.com/odin-lang/Odin/releases/download/dev-$version/odin-windows-amd64-dev-$version.zip"
   }
  }
 },
 "bin": "odin.exe",
 "checkver": {
  "regex": "/releases/tag/dev-([\\d-]+)",
  "url": "https://github.com/odin-lang/Odin/releases/latest"
 },
 "description": "General-purpose programming language with distinct typing, built for high performance, modern systems, and built-in data-oriented data types.",
 "homepage": "https://odin-lang.org/",
 "license": "BSD-3-Clause",
 "version": "2022-12"
}