{
    "architecture": {
        "64bit": {
            "hash": "b5e40f6d41a49eab0b849a5c5c2a2d246b6000b6ebe4d37c7a95da5b08a8a1a8",
            "url": "https://f001.backblazeb2.com/file/odin-binaries/nightly/odin-windows-amd64-nightly%2B2022-09-06.zip"
        }
    },
    "autoupdate": {
        "architecture": {
            "64bit": {
                "url": "https://f001.backblazeb2.com/file/odin-binaries/nightly/odin-windows-amd64-nightly%2B$version.zip"
            }
        }
    },
    "bin": "odin.exe",
    "checkver": {
        "regex": "nightly%2B([\\d\\-]+).zip",
        "reverse": true,
        "url": "https://odinbinaries.thisdrunkdane.io/file/odin-binaries/nightly.json"
    },
    "description": "General-purpose programming language with distinct typing, built for high performance, modern systems, and built-in data-oriented data types.",
    "extract_dir": "windows_artifacts",
    "homepage": "https://odin-lang.org/",
    "license": "BSD-3-Clause",
    "version": "2022-09-06"
}
