{
    "architecture": {
        "32bit": {
            "hash": "d3aa2109bf6241bebafc7263515bb7116b1eb876d0178d2a47d2b73d97232693",
            "url": "https://qemu.weilnetz.de/w32/qemu-w32-setup-20220831.exe#/dl.7z"
        },
        "64bit": {
            "hash": "a8fb81abb85107babcef55925f80c809ae44ac9724b8972ff8df4787ba839dd7",
            "url": "https://qemu.weilnetz.de/w64/qemu-w64-setup-20220831.exe#/dl.7z"
        }
    },
    "autoupdate": {
        "architecture": {
            "32bit": {
                "url": "https://qemu.weilnetz.de/w32/qemu-w32-setup-$matchYear$matchMonth$matchDay.exe#/dl.7z"
            },
            "64bit": {
                "url": "https://qemu.weilnetz.de/w64/qemu-w64-setup-$matchYear$matchMonth$matchDay.exe#/dl.7z"
            }
        },
        "hash": {
            "url": "$urlNoExt.sha512"
        }
    },
    "checkver": "<strong>(?<year>\\d{4})-(?<month>\\d{2})-(?<day>\\d{2})</strong>: New QEMU installers \\((?<version>[\\d.a-z\\-]+)\\)",
    "description": "A generic and open source machine emulator and virtualizer.",
    "env_add_path": ".",
    "homepage": "https://qemu.weilnetz.de/",
    "license": "GPL-2.0-only",
    "version": "7.1.0"
}
