{
 "autoupdate": {
  "url": "https://download.redisant.com/package/RA-$version.exe"
 },
 "checkver": {
  "regex": "RA-([\\d.]+).exe"
 },
 "description": "Redis\u53ef\u89c6\u5316\u7ba1\u7406\u4e0e\u76d1\u63a7",
 "hash": "3d0f3fd55e107496389b438bc660b4a5fbdeb13c0e657e4979b07c11d1fbb00c",
 "homepage": "http://www.redisant.cn/",
 "innosetup": true,
 "license": "Shareware",
 "notes": "Redis Assistant is NOT portable.",
 "shortcuts": [
  [
   "Redis Assistant.exe",
   "Redis Assistant"
  ]
 ],
 "suggest": {
  "dotnet-runtime": "windowsdesktop-runtime"
 },
 "url": "https://download.redisant.com/package/RA-1.1.8.2.exe",
 "version": "1.1.8.2"
}