{
    "architecture": {
        "64bit": {
            "hash": "sha512:bfa5416c951e87346ecc420bace35ad133a126efbfadc511f95f0e314827c5747fda197b09e77b5f1bfccda84630af97e58ffb47d38eba3f67219927a4fe0baf",
            "url": "https://github.com/siderolabs/talos/releases/download/v1.3.3/talosctl-windows-amd64.exe#/talosctl.exe"
        }
    },
    "autoupdate": {
        "architecture": {
            "64bit": {
                "url": "https://github.com/siderolabs/talos/releases/download/v$version/talosctl-windows-amd64.exe#/talosctl.exe"
            }
        },
        "hash": {
            "url": "$baseurl/sha512sum.txt"
        }
    },
    "bin": "talosctl.exe",
    "checkver": {
        "github": "https://github.com/siderolabs/talos"
    },
    "description": "talosctl is a CLI tool which interfaces with the Talos API in an easy manner.",
    "homepage": "https://www.talos.dev",
    "license": "MPL-2.0",
    "version": "1.3.3"
}
