{
 "architecture": {
  "64bit": {
   "hash": "8b6c1da5d90cea52cc3b27cc018afeecc5fae941f2dad2e06e55e76852749919",
   "url": "https://download.vroid.com/dist/4SVwgLvP3X/VRoidStudio-v1.19.0-win.exe"
  }
 },
 "autoupdate": {
  "architecture": {
   "64bit": {
    "url": "https://download.vroid.com/dist/$matchDistid/VRoidStudio-v$version-win.exe"
   }
  }
 },
 "checkver": "https://download.vroid.com/dist/(?<distId>[\\w]+)/VRoidStudio-v(?<version>[\\d.]+)-win\\.exe",
 "description": "3D character maker",
 "homepage": "https://vroid.com/en/studio",
 "innosetup": true,
 "license": {
  "identifier": "Proprietary",
  "url": "https://policies.pixiv.net/en.html#vroidstudio"
 },
 "persist": "uWintab.log",
 "pre_install": "if (!(Test-Path \"$dir\\uWintab.log\")) {New-Item \"$dir\\uWintab.log\" | Out-Null}",
 "shortcuts": [
  [
   "VRoidStudio.exe",
   "VRoid Studio"
  ]
 ],
 "version": "1.19.0"
}