{
 "autoupdate": {
  "extract_dir": "WRCFree_$version",
  "url": "http://downloads.wisecleaner.com/soft/WRCFree_$version.zip"
 },
 "checkver": {
  "regex": "WRCFree.+?([\\d.]+)?\\.zip",
  "url": "https://www.wisecleaner.com/download.html"
 },
 "description": "Clean registry junks, repair Windows errors, and keep your PC at peak performance.",
 "extract_dir": "WRCFree_10.8.2.703",
 "hash": "b973e65b93f445c4f80d942dc1bb046193873968b419b0b1ca1f41fa05a84cb6",
 "homepage": "https://www.wisecleaner.com/wise-registry-cleaner.html",
 "license": "Freeware",
 "persist": [
  "Backup",
  "config.ini"
 ],
 "shortcuts": [
  [
   "WiseRegCleaner.exe",
   "Wise Registry Cleaner"
  ]
 ],
 "url": "http://downloads.wisecleaner.com/soft/WRCFree_10.8.2.703.zip",
 "version": "10.8.2.703"
}