{
    "autoupdate": {
        "url": "https://github.com/bostrot/wsl2-distro-manager/releases/download/v$matchTag/wsl2-distro-manager-v$version.zip"
    },
    "bin": "wsl2distromanager.exe",
    "checkver": {
        "regex": "(?sm)browser_download_url.*?releases/download/v(?<tag>[\\w-.]+)/wsl2-distro-manager-v([\\d.]+)\\.zip",
        "url": "https://api.github.com/repos/bostrot/wsl2-distro-manager/releases/latest"
    },
    "description": "A GUI to quickly manage your WSL2 instances.",
    "hash": "26110c709686ae42fd22419d87cf90375b76cf5bf09167c344396995a9138ce3",
    "homepage": "https://github.com/bostrot/wsl2-distro-manager",
    "license": {
        "identifier": "GPL-3.0-only",
        "url": "https://github.com/bostrot/wsl2-distro-manager/blob/main/LICENSE"
    },
    "shortcuts": [
        [
            "wsl2distromanager.exe",
            "WSL Manager"
        ]
    ],
    "url": "https://github.com/bostrot/wsl2-distro-manager/releases/download/v1.4.0/wsl2-distro-manager-v1.4.0.zip",
    "version": "1.4.0"
}
