{
 "architecture": {
  "32bit": {
   "bin": [
    [
     "x8.32.exe",
     "xinorbis8"
    ]
   ],
   "extract_dir": "XinorbisPro32",
   "hash": "9d655e6b3a4e517ed550e9089f2f0475a80dcb433fca3927102c02b7ae08e9c6",
   "shortcuts": [
    [
     "x8.32.exe",
     "xinorbis8"
    ]
   ],
   "url": "https://downloads.sourceforge.net/project/xinorbis-and-tools/XinorbisPortable_32.zip"
  },
  "64bit": {
   "bin": [
    [
     "x8.64.exe",
     "xinorbis8"
    ]
   ],
   "extract_dir": "XinorbisPro64",
   "hash": "4dc643bb3ba9e500aa03f0b69ecafa362745ee02d056f1c0a667125d4acc576c",
   "shortcuts": [
    [
     "x8.64.exe",
     "xinorbis8"
    ]
   ],
   "url": "https://downloads.sourceforge.net/project/xinorbis-and-tools/XinorbisPortable_64.zip"
  }
 },
 "autoupdate": {
  "architecture": {
   "32bit": {
    "extract_dir": "XinorbisPro32",
    "url": "https://downloads.sourceforge.net/project/xinorbis-and-tools/XinorbisPortable_32.zip"
   },
   "64bit": {
    "extract_dir": "XinorbisPro64",
    "url": "https://downloads.sourceforge.net/project/xinorbis-and-tools/XinorbisPortable_64.zip"
   }
  }
 },
 "checkver": {
  "regex": "dateUpdated\" datetime.*([\\d]{4}-[\\d]{2}-[\\d]{2})</time>",
  "url": "https://sourceforge.net/projects/xinorbis-and-tools/"
 },
 "description": "A very powerful hard disk, folder and storage analyser.",
 "homepage": "https://sourceforge.net/projects/xinorbis-and-tools/",
 "license": "unknown",
 "persist": "custom.ini",
 "version": "2022-11-01"
}