{
    "autoupdate": {
        "url": "https://www.xyplorer.com/download/xyplorer_full_noinstall.zip"
    },
    "checkver": "([\\d.]+), released",
    "description": "XYplorer is a file manager for Windows. It features tabbed browsing, a powerful file search, a versatile preview, a highly customizable interface, optional dual pane, and a large array of unique ways to efficiently automate frequently recurring tasks. It’s fast, light, and portable.",
    "hash": "f8d4f39eab7d1611f35ea6335020d5448b10f980415010fc536bde0ca02e87f0",
    "homepage": "https://www.xyplorer.com",
    "license": {
        "identifier": "Shareware",
        "url": "https://www.xyplorer.com/LicenseXY.txt"
    },
    "notes": "This is a commercial product, with a 30 day trial. For pricing go to: <http://www.xyplorer.com/#buy>",
    "persist": "Data",
    "shortcuts": [
        [
            "XYplorer.exe",
            "XYplorer"
        ]
    ],
    "url": "https://www.xyplorer.com/download/xyplorer_full_noinstall.zip",
    "version": "24.00.0300"
}
