{
    "architecture": {
        "32bit": {
            "extract_dir": "zulu13.54.17-ca-jre13.0.14-win_i686",
            "hash": "3f9633f31a6b188c661fbb8298cc731e9cde04d45e295b5f11835f570ad87237",
            "url": "https://cdn.azul.com/zulu/bin/zulu13.54.17-ca-jre13.0.14-win_i686.zip"
        },
        "64bit": {
            "extract_dir": "zulu13.54.17-ca-jre13.0.14-win_x64",
            "hash": "dd0b7d976f7865ad7bbfbf20650f8cb01860066b779838d8f6938427c02a8fb9",
            "url": "https://cdn.azul.com/zulu/bin/zulu13.54.17-ca-jre13.0.14-win_x64.zip"
        }
    },
    "autoupdate": {
        "architecture": {
            "32bit": {
                "extract_dir": "$matchName_i686",
                "hash": {
                    "jp": "$.sha256_hash",
                    "url": "https://api.azul.com/zulu/download/community/v1.0/bundles/latest/?jdk_version=13&bundle_type=jre&features=headfull&javafx=false&ext=zip&os=windows&arch=x86&hw_bitness=32"
                },
                "url": "https://cdn.azul.com/zulu/bin/$matchName_i686.zip"
            },
            "64bit": {
                "extract_dir": "$matchName_x64",
                "hash": {
                    "jp": "$.sha256_hash",
                    "url": "https://api.azul.com/zulu/download/community/v1.0/bundles/latest/?jdk_version=13&bundle_type=jre&features=headfull&javafx=false&ext=zip&os=windows&arch=x86&hw_bitness=64"
                },
                "url": "https://cdn.azul.com/zulu/bin/$matchName_x64.zip"
            }
        }
    },
    "checkver": {
        "jsonpath": "$.name",
        "regex": "(?<name>zulu(?<version>[\\d.]+)-ca-jre(?<java>[\\d.]+)-win)_x64.zip",
        "replace": "${version}",
        "url": "https://api.azul.com/zulu/download/community/v1.0/bundles/latest/?jdk_version=13&bundle_type=jre&features=headfull&javafx=false&ext=zip&os=windows&arch=x86&hw_bitness=64"
    },
    "description": "Zulu is certified build of OpenJDK",
    "env_add_path": "bin",
    "env_set": {
        "JAVA_HOME": "$dir"
    },
    "homepage": "https://www.azul.com/products/zulu-community/",
    "license": {
        "identifier": "GPL-2.0-only WITH Classpath-exception-2.0",
        "url": "https://www.azulsystems.com/license/zulu_third_party_licenses.html"
    },
    "version": "13.54.17"
}
